setup.py
electronix/__init__.py
electronix/electronix.py
electronix.egg-info/PKG-INFO
electronix.egg-info/SOURCES.txt
electronix.egg-info/dependency_links.txt
electronix.egg-info/top_level.txt