Metadata-Version: 2.1
Name: electronix
Version: 0.0.5
Summary: A basic and simple package for learning about electronics and computer science
Author: VelikiFeniks
Author-email: veliki.feniks@gmail.com
Keywords: python,electronics,computer science,logic gates,binary,ASCII,octal,hex
Classifier: Development Status :: 1 - Planning
Classifier: Intended Audience :: Developers
Classifier: Programming Language :: Python :: 3
Classifier: Operating System :: Unix
Classifier: Operating System :: MacOS :: MacOS X
Classifier: Operating System :: Microsoft :: Windows
